<?xml version="1.0" encoding="UTF-8"?>

<!DOCTYPE note [
<!ENTITY nbsp "&#xA0;">
<!ENTITY writer "Writer: Donald Duck.">
<!ENTITY copyright "Copyright: W3Schools.">
]>


<restaurant>mille et une merveille
    <menu>
        <prix>30 euros</prix>
        <entrées> 
            <entree>Figues rôties au chèvre.</entree>
            <entree>Tajine jben (tajine au fromage)</entree>
            <entree> Saint-Jacques et la poitrine fumée></entree>
        </entrées>
        <plats>
            <plat>Patatas bravas</plat>
            <plat>Paella</plat>
            <plat>Gazpacho</plat>
        </plats>
            <fromage>feuille de chévre</fromage>
            <desserts>
                 <desssert>Piononos de Grenade, Andalousie</desssert>
                 <desssert>Ramequins fondants au chocolat.</desssert>
                 <desssert>Tiramisu (recette originale)</desssert>
            </desserts> 
    </menu>
    <menu>20 euros
        <entrées> 
            <entree>Figues rôties au chèvre.</entree>
            <entree>Tajine jben (tajine au fromage)</entree>        
        </entrées>
        <plats>
            <plat>Patatas bravas</plat>
            <plat>Paella</plat>          
        </plats>   
            <desserts>
                 <desssert>Piononos de Grenade, Andalousie</desssert>
                 <desssert>Ramequins fondants au chocolat.</desssert>               
            </desserts>
    </menu>
        <menu>15 euros
       
            <entree>Tajine jben (tajine au fromage)</entree>
            <plat>Paella</plat>          
            <desssert>Piononos de Grenade, Andalousie</desssert>                    
    </menu>
</restaurant>
